[{"s":0,"e":2.09,"t":"這個第二節，好，第二節。"},{"s":2.09,"e":10.09,"t":"四大短線起漲形態與進出場的策略，什麼意思嘞？就是，呃，我們在剛剛前面一個。"},{"s":10.09,"e":16.36,"t":"小節的時候，好，把這個頭性的，好，頭性的買賣超。"},{"s":16.36,"e":17.48,"t":"嗯。"},{"s":17.48,"e":24.35,"t":"好，頭性的買賣超已經列出來了，對不對？好，我們要怎麼樣從從這裡面每一檔？"},{"s":24.35,"e":33.35,"t":"哦，每一檔去看，哎，哪一個長相，哪一個長相，他是最有機會短線。"},{"s":33.35,"e":40.01,"t":"短線上面有一個波段，就不應該說短線有一個起漲的一個機會。"},{"s":40.01,"e":41.01,"t":"有一個機會。"},{"s":41.01,"e":43.99,"t":"好不好？來，我們先看第一個策略。"},{"s":43.99,"e":52.34,"t":"好，這是我最喜歡的一個長相，哈，就是奇形。好，其實這幾個策略我會放在我們的P P的教學裡面。"},{"s":52.34,"e":54.59,"t":"他會帶蠻多的一個案例。"},{"s":54.59,"e":64.33,"t":"但是我還沒有實際好，實際的好好的把這一個策略，還有那個對應的一個實際的操作的方式。"},{"s":64.33,"e":67.85,"t":"就是詳細的和大家說明過。"},{"s":67.85,"e":77.33,"t":"好，所以就利用，我們就利用這一次機會，好好把他這個用影音的方式給他好好的深入的瞭解一下，講解過一遍，好不好？"},{"s":77.33,"e":78.33,"t":"來。"},{"s":78.33,"e":82.01,"t":"使用情境，使用情境，哈，在很多時候。"},{"s":82.01,"e":83.01,"t":"好，百分之七十。"},{"s":83.01,"e":88.26,"t":"帕以上，我們沒辦法再抓到第一根起漲的那根K棒，哈。"},{"s":88.26,"e":96.59,"t":"除非你他是在盤整的時候，然後你有收到一些訊息，或者是前面有發現一些特別的一些，呃，籌碼的一個進駐。"},{"s":96.59,"e":102.03,"t":"好，不然我們都是看到了的時候，都已經多少七八趴了。"},{"s":102.03,"e":103.03,"t":"好。"},{"s":103.03,"e":112.03,"t":"然後這個時候又怕追高，對不對？那我們怎麼辦？好，我們就使用奇形的觀察方式，很簡單，第一根。"},{"s":112.03,"e":113.03,"t":"然後一。"},{"s":113.03,"e":116.35,"t":"一啊一，然後二三，好，兩根。"},{"s":116.35,"e":125.74,"t":"哦，兩根兩天哦，完成這個形態。好，請看這邊的條件哈。來，第一根它是紅K，實紅哦。"},{"s":125.74,"e":132.09,"t":"可以不用是實紅，沒有關係，它也可以有上影線，它也可以有上影線，也可以的。"},{"s":132.09,"e":136.35,"t":"好，當然不要不要太長了。哦，不要太長，好不好？再來。"},{"s":136.35,"e":144.59,"t":"那個二三好，二三K棒長什麼樣子無所謂的好，收紅收綠也無所謂好。"},{"s":144.59,"e":150.35,"t":"但是他要的原則是什麼？好，紅K，如果他是種紅K的話，他要亮針一點。"},{"s":150.35,"e":157.99,"t":"好，綠K的話，它要什麼樣？量縮，OK。好，然後收盤價，這最重要。"},{"s":157.99,"e":164.35,"t":"哦，這最重要哦，它必須要在什麼五日線之上？這條是五日線，這條是五日線。"},{"s":164.35,"e":165.35,"t":"好，大家不要吵。"},{"s":165.35,"e":173.94,"t":"我這個這個畫作哦，但就是簡單扼要了，簡單扼要。然後呢，我這邊補充，注意聽哦。"},{"s":173.94,"e":176.35,"t":"我這邊補充一個細節。"},{"s":176.35,"e":177.35,"t":"嗯。"},{"s":177.35,"e":180.35,"t":"它的下影線，哦，它的下影線。"},{"s":180.35,"e":184.09,"t":"這些都要在這個紅色的。"},{"s":184.09,"e":192.08,"t":"K棒中間以上，哦，這個是一個非常好的一個長相，哦，非常好的長相。"},{"s":192.08,"e":198.09,"t":"它的下影線就是盤中的低點，要在中間的K棒以上。"},{"s":198.09,"e":206.03,"t":"它的收盤價，兩根二三的收盤價要在第一根的收盤價以上。"},{"s":206.03,"e":214.03,"t":"來，同學們記得，這個是最理想的條件，懂嗎？哦，它二三它的收盤價。"},{"s":214.03,"e":220.35,"t":"可以希望在第一根的收盤價之上。"},{"s":220.35,"e":230,"t":"好，這就超級厲害，超級強，懂嗎？你在二三，你可以在三的地方，就是直接尾盤的時候，哎，觀察一下，做個模擬交易。"},{"s":230,"e":231,"t":"好，進行。"},{"s":231,"e":240.08,"t":"切入這樣子好，然後如果有打下影線的話，不要低於第一根的中間。"},{"s":240.08,"e":241.08,"t":"好。"},{"s":241.08,"e":246.09,"t":"再來，你可以在三的尾盤進去，或者是。"},{"s":246.09,"e":252.35,"t":"四的什麼？它打到盤中，可能切到五日線的位置進場，做一個模擬交易。"},{"s":252.35,"e":255.88,"t":"哦，切入看看，觀察哦。我因為我沒辦法給你這個。"},{"s":255.88,"e":264.01,"t":"確定的買賣的建議，那我們就用這個模擬交易試看看，好觀察一下，好是不是我漲的，呃，這個樣子去走的。"},{"s":264.01,"e":269.77,"t":"好不好？來，你有可能要承受的一個風險是什麼？就是。"},{"s":269.77,"e":270.77,"t":"它有。"},{"s":270.77,"e":274.04,"t":"可能，騎行挑戰失敗。"},{"s":274.04,"e":281.66,"t":"好，變到五的情況，跌破了這個五日線，那很簡單，我們就做離場。"},{"s":281.66,"e":282.66,"t":"好，就說離。"},{"s":282.66,"e":291.1,"t":"瞭解我意思嗎？這是一個完整的策略，你必須要有進場的規劃，也要有出場的條件。"},{"s":291.1,"e":293.09,"t":"停損的條件。"},{"s":293.09,"e":294.09,"t":"瞭解我意思嗎？"},{"s":294.09,"e":295.09,"t":"好好。"},{"s":295.09,"e":297.37,"t":"大概是這個樣子，那。"},{"s":297.37,"e":305.96,"t":"重點在於，如果你是在這個地方切入的話，好；如果你要等第四天切入的話，哦，很可能它可能，呃。"},{"s":305.96,"e":315.54,"t":"第四天，他沒有碰，他就直接上去了，非常有可能。如果他是完成我這個最理想的條件。"},{"s":315.54,"e":318.95,"t":"二三收盤價都在一的收盤價之上的。"},{"s":318.95,"e":327.54,"t":"好二這個三有有有完成二的話都在之上的哈，它很可能第四天開高就直接往上拉，很很有機會。"},{"s":327.54,"e":333.96,"t":"哦，很有機會哦，所以你必須要承受的風險就是，哎，它完全不會達到安全的這個位置。"},{"s":333.96,"e":334.96,"t":"就往上拉了。"},{"s":334.96,"e":335.96,"t":"好，所以你。"},{"s":335.96,"e":345.91,"t":"這樣就可以知道，哎，如果二三是一種很強勢的話，你可以在三的尾盤就做模擬切入哦，就做模擬切入，瞭解我意思嗎？好，這些是一個。"},{"s":345.91,"e":352.2,"t":"這個騎行，好，我們之前在這個Press Play上面教學的時候漏掉。"},{"s":352.2,"e":359.7,"t":"哦，沒有講的一些細節哦，分享給你哦，分享給你，記得哈，要自己做筆記哦，哈。所以你看這個圖上面。"},{"s":359.7,"e":369.56,"t":"是沒有這個細節在上面的，好，因為這個是我們沿用P P的呃教學，但是這個這次的課程，哎，你就會聽到。"},{"s":369.56,"e":375.65,"t":"好，聽到更多的一個細節，瞭解意思嗎？好，好。"},{"s":375.65,"e":384.2,"t":"再來，第一個好，很簡單哈。來，在二零一九年十二月二十四的時候，這一天好，我們就用這個。"},{"s":384.2,"e":391.59,"t":"好，投信買賣超好，你在呃那個富邦的那個券商的，我們剛剛講的。"},{"s":391.59,"e":399.97,"t":"那個地方，好，一樣可以看到同樣的資訊，完全一模一樣，完全一模一樣，哦，所以你不需要，不一定要用這個軟體。"},{"s":399.97,"e":400.97,"t":"好，你點。"},{"s":400.97,"e":402.65,"t":"他，或者是你用其他的。"},{"s":402.65,"e":411.61,"t":"網路上免費的一些呃財經的網站，什麼點進去，你也可以看到它的K棒的，瞭解清楚嗎？所以我會希望就是，哎。"},{"s":411.61,"e":415.7,"t":"你所有的哦，判斷的一個方式哦。"},{"s":415.7,"e":418.2,"t":"找股票、選股的方式，哎，你可以不一定。"},{"s":418.2,"e":419.37,"t":"用這種。"},{"s":419.37,"e":420.37,"t":"可能要付費的。"},{"s":420.37,"e":429.97,"t":"軟體，你可以在網路上有一些很多免費的資源，也一樣可以執行主力大教的所有東西，好，所有東西，瞭解是吧？好，來。"},{"s":429.97,"e":430.97,"t":"嗯。"},{"s":430.97,"e":431.97,"t":"在。"},{"s":431.97,"e":441.47,"t":"在十二月十二十四這一天哈，我們這一天，好，我們盤後，我們盤後的時候，它其實這個頭性已經買了很多天的啦。"},{"s":441.47,"e":449.96,"t":"都沒發動，對不對？好，在這一天，好第一根，第一根。"},{"s":449.96,"e":450.96,"t":"嗯。"},{"s":450.96,"e":454.2,"t":"他這樣好，你一定會看到他，但是我們。"},{"s":454.2,"e":463.65,"t":"通常都是怎麼樣？盤後的時候才會看到它。但其實我講個題外話哦，前面在這邊佈局的時候。"},{"s":463.65,"e":464.65,"t":"前面那邊布。"},{"s":464.65,"e":465.65,"t":"局的時候。"},{"s":465.65,"e":470.96,"t":"我們在這個、這個、這個篩選裡面，就一定可以看得到它了。"},{"s":470.96,"e":479.38,"t":"好，如果你是用主壓的方法的話，你應該可以看到到它。然後，我們可以在這個均線上面做一個安全的試單，好，在安全的試單。"},{"s":479.38,"e":481.97,"t":"在大買的時候，哎，還沒有噴出。"},{"s":481.97,"e":486.95,"t":"哦，這個地方都可以安全的試單，然後非常的，呃，算是很送分題啦。"},{"s":486.95,"e":495.7,"t":"懂嗎？因為大買結果還在這個五日線和十日線的附近，哎，這個地方就會是一個很理想的買點。"},{"s":495.7,"e":501.96,"t":"哦，很理想的買點。好，但是，anyway，我們現在要教學的是。"},{"s":501.96,"e":503.97,"t":"如果我們在盤後看到。"},{"s":503.97,"e":513.7,"t":"一根，哦，我們看到這個狀況，好，他買了三千七百張，哦，然但是他的K棒已經拉出去了，怎麼辦呢？沒關係，哦。"},{"s":513.7,"e":519.65,"t":"記得安全切入，用騎行的方式來下一頁。這邊好。"},{"s":519.65,"e":520.65,"t":"嗯。"},{"s":520.65,"e":526.2,"t":"這邊不動了哈，我們就看這個地方。好，第一根拉出去之後，有沒有？"},{"s":526.2,"e":535.59,"t":"等一天兩天，對不對？好，紅色是有點亮增，綠色怎麼樣？亮縮，對不對？"},{"s":535.59,"e":538.2,"t":"然後再來一點。"},{"s":538.2,"e":541.97,"t":"兩根的收盤價。"},{"s":541.97,"e":551.65,"t":"都在第一根的收盤價之上之上，好現象，對不對？好，好。"},{"s":551.65,"e":552.65,"t":"沒有問題。"},{"s":552.65,"e":554.2,"t":"我們可以在這一天的。"},{"s":554.2,"e":555.65,"t":"尾盤。"},{"s":555.65,"e":556.65,"t":"做模擬。"},{"s":556.65,"e":557.65,"t":"切入，好。"},{"s":557.65,"e":567.36,"t":"我們這邊都是用模擬切入哈，因為我們這邊不會跟你講建議要怎麼樣做哦，但是你就，呃，自己知道就可以了。這邊都是用模擬模擬的交易。"},{"s":567.36,"e":576.75,"t":"好，在這邊哦，你看哦，如果我們是用安全的方式的話，其實它第四天是打不到五日線的。"},{"s":576.75,"e":577.75,"t":"好，有沒有發現？"},{"s":577.75,"e":585.34,"t":"你必須要承受的呃機會風險，就是你可能在五日線沒辦法有一個安全的切入，它就會。"},{"s":585.34,"e":588.72,"t":"拉上去，拉上去，OK。"},{"s":588.72,"e":597.85,"t":"那你短線上面，哎，跌破五日線你就出場也沒有問題。OK，就稍微的，哎，賺個十幾趴，然後十幾趴也不錯，哦，也不錯的。"},{"s":597.85,"e":603.85,"t":"OK，好，再來下一個。"},{"s":603.85,"e":609.35,"t":"好，南帝，好南帝，你在這一天，哦，我們在這一天。"},{"s":609.35,"e":615.6,"t":"看到他哎，買七百多張哦，買七百多張，好，但是他並沒有，還有並沒有拉出一根。"},{"s":615.6,"e":619.85,"t":"很漂亮的實體紅K，直到哪一天？直到。"},{"s":619.85,"e":627.85,"t":"這一天沒有問題，對不對？好，我記得哦，我們發現了這一根。"},{"s":627.85,"e":635.35,"t":"好，法人進駐之後，你要把它放起來觀察，哦，放到你的自選股裡面去做觀察。"},{"s":635.35,"e":643.29,"t":"瞭解我意思嗎？好，你要放進去觀察，然後看它到底哪一天，哎，可以拉出一根紅K。"},{"s":643.29,"e":648.61,"t":"表態的紅K，然後量增，然後實體紅K比那個上影線還要多。"},{"s":648.61,"e":657.22,"t":"這樣子就是一個不錯的一個樣子。好，再來拉出來之後，記得好，我們隔天不用追高，我們就是等兩天。"},{"s":657.22,"e":665.35,"t":"好，一二，好，一二，來，一樣，完全走的一模一樣，有沒有看到？"},{"s":665.35,"e":673.35,"t":"好，紅色的量增，好，綠色的量縮，OK。"},{"s":673.35,"e":683.29,"t":"收盤價，哦，在第一根的收盤價之上，非常強勢的一個象徵。第二點。"},{"s":683.29,"e":684.29,"t":"哦。"},{"s":684.29,"e":689.35,"t":"上影線呃，下影線在紅K的一半。"},{"s":689.35,"e":697.26,"t":"以上，好的，我們就是可以在這一根綠K的尾盤做模擬切入。"},{"s":697.26,"e":705.3,"t":"好，我們這樣就非常符合一個旗子旗杆的一個情況，哦，算是一個很送分題的，啊，這樣。"},{"s":705.3,"e":706.3,"t":"好，瞭解意思嗎？"},{"s":706.3,"e":707.61,"t":"好。"},{"s":707.61,"e":708.61,"t":"好。"},{"s":708.61,"e":717.35,"t":"隔天又拉出一根很漂亮的紅K，對不對？那這一次就是非常的標準。"},{"s":717.35,"e":721.12,"t":"這一次就是非常的標準，它打到五日線來接人。"},{"s":721.12,"e":729.85,"t":"對不對？來打到五日線來接人，好，大家都可以回去看這個二零二零年十月十三號這邊的走勢，這邊的走勢，OK。"},{"s":729.85,"e":737.3,"t":"好，這邊又拉出一根嘍，好，就跟複製的，好，複製的第一根旗杆又出來了，OK。"},{"s":737.3,"e":738.3,"t":"嗯。"},{"s":738.3,"e":745.03,"t":"好，這邊拉出來之後，第一根後後面第二根拉出來，後面就完全沒有。"},{"s":745.03,"e":753.85,"t":"呃，第二根就完全沒有在那個量縮手穩了，懂嗎？同學們記得哦。呃，你不會每次都會有這種。"},{"s":753.85,"e":755.27,"t":"拉一根。"},{"s":755.27,"e":756.27,"t":"然後休息兩。"},{"s":756.27,"e":761.03,"t":"天再拉一根，休息兩天的情況，好，你有可能，哎，我們。"},{"s":761.03,"e":769.32,"t":"前面佈局了一下下之後，後面就會直接噴出去，懂嗎？它不會走一，然後休息兩天，它可能走一個一二。"},{"s":769.32,"e":779.27,"t":"直接往上拉的情況，哦，瞭解意思嗎？哈，主力大這邊教學的都是希望各位用一個非常標準的一個安全的，好，安全的。"},{"s":779.27,"e":785.3,"t":"哦，方式做切入，但是它有可能，第二天就直接拉出去了啊，也有可能，好不好？"},{"s":785.3,"e":786.3,"t":"嗯。"},{"s":786.3,"e":795.24,"t":"下一個好，拉出來之後，哎，隔天，哦，來，一、二、三。"},{"s":795.24,"e":803.61,"t":"好，沿著還是沿著這一個五日線這邊做一個那個旗形出來了。"},{"s":803.61,"e":811.61,"t":"對不對？哦，這邊又一個奇形嘍，這邊又出現一個奇形嘍，好，所以。"},{"s":811.61,"e":812.61,"t":"嗯。"},{"s":812.61,"e":817.15,"t":"綠K好，跟第一根比好，我們這邊是量縮，對不對哈？"},{"s":817.15,"e":824.6,"t":"然後後面啊，後面雖然沒有很理想，對不對？這兩根沒有很理想，都是量縮的啊，但是它至少維持在。"},{"s":824.6,"e":825.6,"t":"這個。"},{"s":825.6,"e":829.02,"t":"五日線之上，好，勉強這根就比較勉強。"},{"s":829.02,"e":830.02,"t":"對不對？沒關係。"},{"s":830.02,"e":839.61,"t":"西，後面這一根還不錯，哦，還不錯。我們在這個地方尾盤，你可以做切入。為什麼嘞？因為它至少這個整個形態、整個樣子沒有破。"},{"s":839.61,"e":844.86,"t":"棋子，好，棋子，好。"},{"s":844.86,"e":845.86,"t":"嗯。"},{"s":845.86,"e":850.4,"t":"這邊切入之後，下一個好，又拉出一個旗杆。"},{"s":850.4,"e":856.39,"t":"又拉出一個旗杆，好，很漂亮的旗杆。再來，旗杆之後。"},{"s":856.39,"e":857.39,"t":"又。"},{"s":857.39,"e":858.96,"t":"是，呃，二。"},{"s":858.96,"e":860,"t":"三四。"},{"s":860,"e":867,"t":"好，我們這邊是走二三四，好，第四根，好，又沿著這個旗子，好，這個就是一直重複。"},{"s":867,"e":870.39,"t":"一直重複。"},{"s":870.39,"e":872,"t":"嗯。"},{"s":872,"e":881.78,"t":"有沒有？好，一直重複，再來，又拉出一根旗杆。好，我不知道大家已經對這個慣性，已經不知道有沒有熟悉了。"},{"s":881.78,"e":890.94,"t":"好，第一根旗杆又出來了。再來，我們剛剛是在這邊嘛？哈，好，這邊第一個棋子。"},{"s":890.94,"e":891.94,"t":"第二個，其實第三。"},{"s":891.94,"e":901.26,"t":"這個旗子後面往上拉拉拉，一直往上拉。好，在這一根好，我們就做一個出場，因為怎麼樣，它跌破了五日線。"},{"s":901.26,"e":902.26,"t":"嗯。"},{"s":902.26,"e":909.46,"t":"好，把這下面的你看哦，我們在五十六進去，這邊已經到了七十塊。好，短短的。"},{"s":909.46,"e":914.94,"t":"一個月，哦，短短的一個月，這應該五個交易額，三個禮拜。"},{"s":914.94,"e":915.94,"t":"好，十五個交易。"},{"s":915.94,"e":925.5,"t":"十十個呃十五個交易日左右，好三個禮拜，這樣子從五十五到七十啊，五十五到七十。"},{"s":925.5,"e":933,"t":"OK，好，這就是一個短線的短線的一個交易，好，非常的，呃，有一個SOP。"},{"s":933,"e":940.92,"t":"好，非常的那個送分題，對不對？好，好，這個案例，如果還覺得。"},{"s":940.92,"e":947,"t":"不清楚的話，沒問題，我們再講一個。好，一樣是南帝，一樣是南帝。"},{"s":947,"e":954.68,"t":"OK，在這一天三月十八號的時候，哎，頭信又進來買了。"},{"s":954.68,"e":961.26,"t":"這邊，對不對哦？你看到它了哦，你看到它了，哎，這邊可能。"},{"s":961.26,"e":969.32,"t":"哎，十三呃，三月十八號，OK，在這邊你可以看到，哎，他有買七十五張，可能這邊數字不沒有對到，不過。"},{"s":969.32,"e":973.5,"t":"重點是在這邊，好，你有買看到它買在這個位置，好，觀察它。"},{"s":973.5,"e":976.96,"t":"好，買了之後。"},{"s":976.96,"e":986.75,"t":"它很可惜，沒有讓我們有一個安全的隔一天，沒有安全的切入，它直接拉一根，對不對？好，拉一根就算了哈，後面又再拉一根。"},{"s":986.75,"e":994.68,"t":"但是，安全的點就是這個地方，有沒有一個騎行？"},{"s":994.68,"e":997.26,"t":"又出來了。"},{"s":997.26,"e":1004.69,"t":"樣子，這個樣子一定要符合，懂嗎？哦，下面都是多頭，多頭的排列，這是不用毫無疑問的。"},{"s":1004.69,"e":1005.69,"t":"對不對？哈。"},{"s":1005.69,"e":1013.28,"t":"來拉一根之後，後面兩根紅K，紅K都是永遠都是比綠K還好，懂嗎？紅K絕對會比。"},{"s":1013.28,"e":1018.94,"t":"整理的時候的紅K絕對都會比日那個綠K還要來得好。"},{"s":1018.94,"e":1021.26,"t":"好，我們在這一天。"},{"s":1021.26,"e":1025.26,"t":"可以尾盤，可以做模擬的切入，對不對？"},{"s":1025.26,"e":1028.92,"t":"好，我們剛剛在，剛剛在哪邊？剛剛在這邊。"},{"s":1028.92,"e":1034.88,"t":"同學們，在這，在這，對吧？哦。"},{"s":1034.88,"e":1042.99,"t":"直接從這邊是多少？看一下，網上看一下哦。這個地方七十五塊哦，在這邊看到它。"},{"s":1042.99,"e":1050.94,"t":"七十五，到這邊的時候已經八十五了。好，短短四天八十五，但是我們都比較沒有一個很照我們。"},{"s":1050.94,"e":1060.88,"t":"這個七星策略的SOP進場啊，只有到直到這一天啊，中間這個地方都直接拉兩根上去啊，比較比較急一點啊，但是沒關係，我們在這個地方。"},{"s":1060.88,"e":1066.94,"t":"八十五塊的時候，還可以做一個安全的切入。好，八十五，下一張。"},{"s":1066.94,"e":1067.94,"t":"好，從這邊。"},{"s":1067.94,"e":1077.5,"t":"八股直接往上走，一樣哦，只有短短的几几個幾個交易日哦，幾個交易日從八股走到。"},{"s":1077.5,"e":1081.26,"t":"一百七十塊，走到一百七十塊，好。"},{"s":1081.26,"e":1090.94,"t":"一路都可以加碼，怎麼加碼嘞？你看這邊又拉出第一根，後面休息兩兩天，又這邊又是一個奇形，這一根。"},{"s":1090.94,"e":1098.94,"t":"有發現嗎？這個地方又是一個奇形，這邊是第一個，哦，這邊是第一個。"},{"s":1098.94,"e":1106.94,"t":"這邊是第二個，對不對？哦，然後有符合我們的原則。"},{"s":1106.94,"e":1107.94,"t":"嗯。"},{"s":1107.94,"e":1109.5,"t":"哦。"},{"s":1109.5,"e":1110.95,"t":"最強勢的原則。"},{"s":1110.95,"e":1120.89,"t":"好，拉出紅K之後，二三的收盤價都在第一根之上，而且它離五日線沒有很遠啊，做一個量縮的整理，好，安全的。"},{"s":1120.89,"e":1125.26,"t":"做模擬切入，直接拉上去，所以這段就有兩次的。"},{"s":1125.26,"e":1128.04,"t":"一個切入的，騎行切入的機會。"},{"s":1128.04,"e":1136.04,"t":"好，非常的，呃，怎麼講，SOP啦，哦，非常的SOP，所以你會覺得很難嗎？並沒有，對不對？"},{"s":1136.04,"e":1144.04,"t":"好，我們第二個，第二個我們要講什麼？反轉的形態。好，反反轉的形態。"},{"s":1144.04,"e":1152.04,"t":"這個是反轉形態的進出策略，我們這邊有一個圖例給各位，好，我們一帶各位一起看。"},{"s":1152.04,"e":1161.9,"t":"這個策略最主要的目的在於趨勢反轉，抓到安全的切入點。我們馬上來看一下這個使用的情境啊。"},{"s":1161.9,"e":1171.14,"t":"第一個哈，一路下跌的K棒，我們不會進去接好，直到出現一根反轉趨勢的紅K，而我們通常。"},{"s":1171.14,"e":1174.64,"t":"第一天可以看到的，看到的時候。"},{"s":1174.64,"e":1180.51,"t":"可以去搶一個隔日蟲，就是你尾盤做切入，然後隔天開盤把它賣掉。"},{"s":1180.51,"e":1190.46,"t":"叫隔日衝，對不對？好，但是因為呢，為什麼要把賣掉？因為左邊的壓力通常很大，所以常常哈會回造成回跌。"},{"s":1190.46,"e":1198.9,"t":"好，當然也有少部分的情況，哎，反轉之後一路向上的也有。不過我們這邊強調的是一個安全的切入點。"},{"s":1198.9,"e":1206.9,"t":"好不好？安全的策略好。左方壓力大小取決於以下兩點：好，趨勢向下。"},{"s":1206.9,"e":1215.15,"t":"的K棒高點去把它連線起來，哦，斜率越斜的話，它的壓力就會越大，哦，這麼呃。"},{"s":1215.15,"e":1220.48,"t":"呃，大概怎麼樣？這個部分你就必須要用這個肉眼去做判斷。好，第二個。"},{"s":1220.48,"e":1221.48,"t":"左方的。"},{"s":1221.48,"e":1230.37,"t":"K棒通常量都很大，在上方啊。我們之前在呃K棒教學有講過，量價關係裡面有講過第二章的。"},{"s":1230.37,"e":1239.15,"t":"第三節，好，左那個左方越多的大量K棒，好在上面股價的上方，代表說這邊都是壓力。"},{"s":1239.15,"e":1240.64,"t":"對吧？哦。"},{"s":1240.64,"e":1250.52,"t":"第二個，這個形態哦，通常均線都會很亂，好，但是我們要的長相是三條均線，好，至少。"},{"s":1250.52,"e":1254.53,"t":"五十、二十要在這個下面，這邊是三條均線，我畫的。"},{"s":1254.53,"e":1259.14,"t":"這個示意圖，好，反轉紅K要站上所有的。"},{"s":1259.14,"e":1260.33,"t":"均線。"},{"s":1260.33,"e":1261.33,"t":"要求也是蠻好。"},{"s":1261.33,"e":1267.12,"t":"短均線皆要開始上彎，用扣底值判斷，最好原本就為多頭排列。"},{"s":1267.12,"e":1275.89,"t":"哎，如果這邊不會扣底值的話，沒關係。在我們的那個專案的策略裡面，有這個教學哦，有這個教學。"},{"s":1275.89,"e":1284.65,"t":"在這個首頁的地方，好，首頁的地方點入主力策略，好，主力策略。"},{"s":1284.65,"e":1292.59,"t":"總整理這個部分啊，我們有完整的一個扣底教學預判的方式啊，預判的方式。"},{"s":1292.59,"e":1293.59,"t":"好，我們。"},{"s":1293.59,"e":1294.9,"t":"回來，我們繼續的哈。"},{"s":1294.9,"e":1295.9,"t":"嗯。"},{"s":1295.9,"e":1302.61,"t":"來看這邊圖哦，右邊這邊紅K底部需站上下降趨勢線。"},{"s":1302.61,"e":1308.56,"t":"這條，把這個高點連線的高點連線的這邊，好。"},{"s":1308.56,"e":1310.57,"t":"然後點連線的，再來。"},{"s":1310.57,"e":1311.57,"t":"紅黑。"},{"s":1311.57,"e":1312.58,"t":"底部。"},{"s":1312.58,"e":1314.53,"t":"需站上所有均線。"},{"s":1314.53,"e":1322.91,"t":"好，重點對不對？好，第三個哦，安全的切入點在反轉紅K的下方三分之一處，這個位置比較。"},{"s":1322.91,"e":1330.91,"t":"安全，好，是我們的一個安全的切入點。好，你可以做模擬交易試看看。好，停損就為什麼？"},{"s":1330.91,"e":1335.15,"t":"這一根紅K的低點啊，只要。"},{"s":1335.15,"e":1338.91,"t":"呃，這樣子。"},{"s":1338.91,"e":1348.59,"t":"哦，K棒變成這樣子哈，收盤價已經低於了這一個紅K的低點的價格，哎，我們就做離場，我們就做離場。"},{"s":1348.59,"e":1356.53,"t":"好，換言之，如果你越靠近紅K的低點切入，風險就會越小，成本就會越越越低啊。"},{"s":1356.53,"e":1358.91,"t":"以最小的風險。"},{"s":1358.91,"e":1365.14,"t":"換取最大的獲利策略，這就是一個我們剛剛講的風暴比的一個概念。"},{"s":1365.14,"e":1370.91,"t":"好，你可以去查“風暴筆”的概念。好，切入的切入後的停利點。"},{"s":1370.91,"e":1374.4,"t":"則為跌，呃，我看一下，跌破。"},{"s":1374.4,"e":1380.33,"t":"昨天點這個應該是切入後的停損點啊，就是跌跌破這個。"},{"s":1380.33,"e":1388.59,"t":"好，不是停利，好是停損的位置，就是這一根的低點，好不好？來，我們馬上看例項，然後馬上看例項。"},{"s":1388.59,"e":1389.59,"t":"嗯。"},{"s":1389.59,"e":1397.14,"t":"好，陣容陣容，來一樣哈，我們會在這個這個。"},{"s":1397.14,"e":1402.91,"t":"這個這個這個地方啊，我們在這個這個地方啊，我們可以，如果你在。"},{"s":1402.91,"e":1408.16,"t":"呃，投信，在投信的選股裡面啊，選股裡面。"},{"s":1408.16,"e":1409.16,"t":"你會發現。"},{"s":1409.16,"e":1411.68,"t":"哎，他在這一天。"},{"s":1411.68,"e":1413.69,"t":"有買超。"},{"s":1413.69,"e":1421.69,"t":"對不對？哦，它在這個地方有買超哦，然後我們再判斷一下它整個下降趨勢的。"},{"s":1421.69,"e":1422.69,"t":"怎麼畫？"},{"s":1422.69,"e":1425.69,"t":"怎麼畫？來，這個樣子。"},{"s":1425.69,"e":1430.29,"t":"嗯。"},{"s":1430.29,"e":1435.29,"t":"這樣哦，你把兩根的什麼高點？"},{"s":1435.29,"e":1444.29,"t":"兩根的高點連線起來，就這樣畫下來。兩根高點畫下來。"},{"s":1444.29,"e":1454.24,"t":"瞭解我意思嗎？哦，那我們的安全的切入點在哪個地方嘞？就在紅K的下緣三分之一處。"},{"s":1454.24,"e":1455.24,"t":"你們。"},{"s":1455.24,"e":1464.79,"t":"錯，沒錯嘛，哈，三分之一處。好，我們看一下下一章。來，隔天我們可以在它的這個下下緣的地方。"},{"s":1464.79,"e":1468.56,"t":"做安全的切入，我們停損非常簡單。"},{"s":1468.56,"e":1472.79,"t":"就是在這一根紅K的低點跌破，對不對？"},{"s":1472.79,"e":1480.55,"t":"首先呢，同學們，首先你要先判斷第一個哦，這個兩個高點連線。"},{"s":1480.55,"e":1488.56,"t":"兩個高點連線畫下來，好，有反轉的這個突破下降趨勢。第二個。"},{"s":1488.56,"e":1494.24,"t":"所有的均線，五十二、十、六、十、五、十、二十都在。"},{"s":1494.24,"e":1501.56,"t":"這個整根的K棒之下，這個非常重要，它所有的均線一定要在。"},{"s":1501.56,"e":1508.51,"t":"這個紅K的下面不可以被任何切到，瞭解意思嗎？好好符合這個狀態之後嘞。"},{"s":1508.51,"e":1518.21,"t":"隔一天，我們可以在紅K的低點，哦，紅K下緣，哦，三分之一處的地方，哦，進行模擬切入，啊，模擬切入。"},{"s":1518.21,"e":1526.24,"t":"好，後面拉出一根，馬上就拉出一根哦，給我們看，對不對？"},{"s":1526.24,"e":1528.22,"t":"哦，這就是第一根。"},{"s":1528.22,"e":1534.79,"t":"好，第一根，哎，那你會去思考一件事情哦，這邊紅K拉出了第一根。"},{"s":1534.79,"e":1544.74,"t":"哦，五十二十也排列的不錯，對不對？多頭排列，它這樣的狀態是不是就符合我們講的什麼期型的一個情況？"},{"s":1544.74,"e":1550.24,"t":"騎行的一個情況。"},{"s":1550.24,"e":1551.24,"t":"對不對？"},{"s":1551.24,"e":1552.79,"t":"兩根收盤價。"},{"s":1552.79,"e":1556.56,"t":"哎，這這邊的情況是兩根的收盤價大於什麼？"},{"s":1556.56,"e":1564.79,"t":"第一根的收盤價非常強，非常強勢的情況，好，那我們就在。"},{"s":1564.79,"e":1568.55,"t":"可以在第三天，一二三，第三天的。"},{"s":1568.55,"e":1572.56,"t":"收盤價進行模擬切入，對不對？好。"},{"s":1572.56,"e":1582.05,"t":"然後下面頭新也是繼續買，這個你都可以在那個公開的資料裡面找到它，找到這些資訊，你就會篩出來，然後符合了籌碼。"},{"s":1582.05,"e":1584.56,"t":"符合了籌碼面，我們就用。"},{"s":1584.56,"e":1585.56,"t":"我們教的。"},{"s":1585.56,"e":1591.97,"t":"好，奇形或者是反那個反轉等等的，好，後面還會教其他的形態。"},{"s":1591.97,"e":1596.56,"t":"好，又拉出一根，又拉出一根旗杆。"},{"s":1596.56,"e":1599.96,"t":"對不對？哦，這樣子，短線上面就已經有開始獲利了。"},{"s":1599.96,"e":1608.06,"t":"哦，後面走到哪就不知道。好，反正就跌破了五日線，就可以離開。好，反轉讓我們確立、確確立了這個。"},{"s":1608.06,"e":1616.29,"t":"這個買入的成本好很低以外，好，我們後面後續就沿用其他的策略好進行操作，好，如果它符合的。"},{"s":1616.29,"e":1622.18,"t":"我們要的情況的話，大家瞭解我意思嗎？哦，好，再來，來。"},{"s":1622.18,"e":1630.24,"t":"本節重點，均線啊，反轉的均線，注意聽哦，反轉的均線，你不能切到K棒。"},{"s":1630.24,"e":1631.24,"t":"嗯。"},{"s":1631.24,"e":1640.56,"t":"哦，K棒拉起來的時候，這條所有的均線不能被不能切到這個K棒。好，來高點。"},{"s":1640.56,"e":1648.55,"t":"哦，高點這樣子畫線畫下來，沒有問題，對不對？哦，這樣畫下來，你會發現，哎，首先。"},{"s":1648.55,"e":1654.24,"t":"這個下降趨勢線，這個下降趨勢線已經切到K棒，它不是。"},{"s":1654.24,"e":1656.56,"t":"在紅黑的。"},{"s":1656.56,"e":1660.56,"t":"底部，這個就失敗。第二個。"},{"s":1660.56,"e":1661.56,"t":"二十元每。"},{"s":1661.56,"e":1668.56,"t":"這一條線也切到了均線，失敗，啊，這就不成立。"},{"s":1668.56,"e":1672.55,"t":"好，為什麼不成立嘞？我馬上往下看。"},{"s":1672.55,"e":1678.24,"t":"這邊漲勢就比較短，馬上就下跌，好，很容易就失敗。"},{"s":1678.24,"e":1686.18,"t":"很容易就失敗，對不對？好，我們繼續往下看，同一檔哦，同一檔，這個頭型也繼續買。"},{"s":1686.18,"e":1689.81,"t":"好，直到哪一邊？來，我們再畫一次。"},{"s":1689.81,"e":1690.81,"t":"嗯。"},{"s":1690.81,"e":1694.2,"t":"兩條高點連線，好。"},{"s":1694.2,"e":1703.34,"t":"這樣子，兩條高，呃，兩個高點，這邊高點還有這邊高點連線畫下來，在這一天。"},{"s":1703.34,"e":1704.34,"t":"好。"},{"s":1704.34,"e":1705.34,"t":"符合了第一個。"},{"s":1705.34,"e":1706.69,"t":"第一個。"},{"s":1706.69,"e":1715.26,"t":"怎麼樣？突破了下降的趨勢線，第二個均線都在這個紅K的下方，對不對？"},{"s":1715.26,"e":1723.61,"t":"只不過差別在於說，哎，這一次的機會可能比較小一點。為什麼嘞？因為它的均線已經開始發散了。"},{"s":1723.61,"e":1730.2,"t":"已經開始發散了，他們不是像我們上一個陣容那麼好糾結在一起，所以他可能比較不會。"},{"s":1730.2,"e":1735.94,"t":"回撤到比較深，呃，比就後下面的位置，哦，瞭解意思嗎？"},{"s":1735.94,"e":1743.89,"t":"好，所以我們看到的地方在哪邊？我們剛看到地方在這。"},{"s":1743.89,"e":1744.89,"t":"在。"},{"s":1744.89,"e":1753.88,"t":"一根，對不對？哦，因為他已經開始走出他的格局了，哦，所以他比較沒有機會，哎，在做。"},{"s":1753.88,"e":1762.16,"t":"下緣的整理，它直接就拉出去了哦。但是形態上面符合之後，還是有一個短波的行情。"},{"s":1762.16,"e":1770.44,"t":"短波的行情好，但這邊重點就是要跟各位講哈，這個均線還有下降趨勢線。"},{"s":1770.44,"e":1778.2,"t":"不要切到我們的反轉紅K，OK，再來下一個經濟。"},{"s":1778.2,"e":1785.86,"t":"好，我們在這一天啊，在這一天，很多天吶，很多天都可以看到有經濟的。"},{"s":1785.86,"e":1786.86,"t":"在投信的。"},{"s":1786.86,"e":1794.21,"t":"呃，買超裡面的身影哦，前幾大對不對？這邊排序下來，哦，第九名哦，第九名，好，都看到他。"},{"s":1794.21,"e":1799.94,"t":"但是呢，我們每次畫線，它都過不了。來，這邊畫。"},{"s":1799.94,"e":1801.85,"t":"好，過來。"},{"s":1801.85,"e":1807.94,"t":"哦，沒有過。好，我們繼續看，繼續盯著嘛。好，我們同學們就去盯著。好，下一條線。"},{"s":1807.94,"e":1817.84,"t":"哎，畫過來，畫下來，有沒有看到？打到這個上緣，打到這個上緣，好，就說就收了這個上影線，再往下。"},{"s":1817.84,"e":1818.84,"t":"嗯。"},{"s":1818.84,"e":1821.81,"t":"這邊好，隔天收一個黑K。"},{"s":1821.81,"e":1830.2,"t":"這個也是有個黑K，好，再繼續下一天，這就是每一天的進展。我給你看的就是每一天進展。哎，這一天突破了。"},{"s":1830.2,"e":1831.87,"t":"嗯。"},{"s":1831.87,"e":1839.94,"t":"這邊突破了，好，那就使用我們的什麼反轉的下緣，反轉的下緣，對不對？好。"},{"s":1839.94,"e":1847.83,"t":"這是放大圖，這是放大圖。好，剛剛從這個地方切下來了。好，我們在這個區域。"},{"s":1847.83,"e":1855.89,"t":"它紅K這個K棒的三分之一處，好，有非常多次的機會。"},{"s":1855.89,"e":1863.89,"t":"哦，進行切入，對不對？好，停損我們怎麼設嘞？停損就是設這一根K棒。"},{"s":1863.89,"e":1864.89,"t":"收。"},{"s":1864.89,"e":1871.94,"t":"盤價低於反轉紅K的低點的價格。"},{"s":1871.94,"e":1881.86,"t":"沒有問題，對不對？好，好，再來。你看這個地方非常多的機會，好，非常多的機會。"},{"s":1881.86,"e":1882.86,"t":"嗯。"},{"s":1882.86,"e":1890.2,"t":"哦，直接就波段行情就直接上去了，好，波段行情就直接上去了，對不對？"},{"s":1890.2,"e":1894.39,"t":"好，那這個就是我們反轉的紅K的。"},{"s":1894.39,"e":1903.94,"t":"的策略反轉紅黑的策略是不是非常簡單？好，非常簡單。好，下一個部分，好，下一個部分是我非常喜歡的。"},{"s":1903.94,"e":1907.94,"t":"一個策略，好，我們來看一下。"},{"s":1907.94,"e":1917.81,"t":"好，布林上軌進出策略，好，這個看起來是已經有點糊掉了啊，有點糊掉，但是我們很快的，好把這個可以。"},{"s":1917.81,"e":1922.44,"t":"講解過去，來，好好幫你個解解釋一下哈，來。"},{"s":1922.44,"e":1927.2,"t":"抓住標股齊漲的策略教學，來注意此策略就。"},{"s":1927.2,"e":1935.2,"t":"具備什麼追加的風險，請評估自身風險承受度。OK，前置條件哈，通道好，我們看到這邊。"},{"s":1935.2,"e":1943.62,"t":"布林通道，好，布林通道，同學們先講一下布林通道。布林通道的話，你在那個你的券商裡面，哦。"},{"s":1943.62,"e":1949.94,"t":"一定下單軟體裡面一定會看，一定有這個叫做 B B Band 啊，應該沒有問題哈。"},{"s":1949.94,"e":1959.89,"t":"那個你不沒有沒有找到的話，你可以去問一下你的營業員，好不好？好，通道好，我們再看到通道。"},{"s":1959.89,"e":1960.89,"t":"不可以為。"},{"s":1960.89,"e":1962.21,"t":"下降趨勢。"},{"s":1962.21,"e":1971.46,"t":"它不可以是這樣通這個通道，好，它最好是平橫盤的壓縮，好，這個部分跟大家。"},{"s":1971.46,"e":1972.46,"t":"做一個說明。"},{"s":1972.46,"e":1973.46,"t":"好不好？"},{"s":1973.46,"e":1976.59,"t":"它最好是橫盤的，它不能是往下的通道。"},{"s":1976.59,"e":1984.99,"t":"懂嗎？好，橫盤再來，上升趨勢哦，上升趨勢這種比較沒有爆發力的哈，橫盤的最優，OK。"},{"s":1984.99,"e":1986.09,"t":"下降趨勢。"},{"s":1986.09,"e":1987.09,"t":"就是我們。"},{"s":1987.09,"e":1995.85,"t":"直接教原本的那個反轉的策略就可以了，所以這兩個，哦，就是它的一個限制條件，哦，上升趨勢它如果。"},{"s":1995.85,"e":2004.84,"t":"通通出去的話，哎，它可能爆發力沒這麼強。那向上趨勢的話，我們不用這個策略，我們用反轉策略就可以了。OK，好，再來。"},{"s":2004.84,"e":2007.86,"t":"通道有分，通道頂就是上軌。"},{"s":2007.86,"e":2015.59,"t":"中軌、中線就是二十MA，就是你的月線，通到底就是下軌。好，這三這三個地方，你一定在。"},{"s":2015.59,"e":2019.85,"t":"你的券商軟體可以看得到，好，同學們這邊有跟上嗎？"},{"s":2019.85,"e":2020.85,"t":"有跟上嗎？"},{"s":2020.85,"e":2024.85,"t":"好，就是布林通道了。好，再來。"},{"s":2024.85,"e":2033.08,"t":"股價起漲前，哦，上下通道是越窄越好。什麼叫做窄？我這邊給你定義，哦，上軌。"},{"s":2033.08,"e":2035.85,"t":"減掉下軌，除以中間中軌。"},{"s":2035.85,"e":2041.59,"t":"小於十趴，哦，那它代表說，這一個就會是一個不錯的。"},{"s":2041.59,"e":2050.09,"t":"一個窄度，窄度越窄，它爆發力的話，它後面延續性越強。瞭解意思嗎？好，我們看這邊第一個。"},{"s":2050.09,"e":2053.34,"t":"起漲紅K，它這邊已經突出去了。"},{"s":2053.33,"e":2061.59,"t":"好，記得收盤價一定要高過這個上軌的位置，收盤價也要高過上軌，瞭解嗎？而且一定要帶量，下面一定要帶量。"},{"s":2061.59,"e":2065.54,"t":"好，然後它出出去之後，我們就要看一下它前一天。"},{"s":2065.54,"e":2066.54,"t":"好，記得哦。"},{"s":2066.54,"e":2073.54,"t":"這個策略不用提前佈局，同學們這邊記得哦。這是一個細節，這邊是一個細節啊。"},{"s":2073.54,"e":2074.54,"t":"嗯。"},{"s":2074.54,"e":2083.85,"t":"這個策略不需要提前佈局，它是要確立已經突破了之後，我們再來算。哎，它前一天有沒有小於十趴？"},{"s":2083.85,"e":2087.85,"t":"前一天沒小於十趴，然後就是說，你要算它。"},{"s":2087.85,"e":2095.85,"t":"突破完之後的前一天，上下的窄度哦，頻寬有沒有？通道窄度有沒有小於十帕？"},{"s":2095.85,"e":2097.59,"t":"OK，好。"},{"s":2097.59,"e":2107.4,"t":"再來，有突出突出去之後，當天尾盤是一個買點，好，你可以做模擬交易。再來，第二個，好，次日的上軌。"},{"s":2107.4,"e":2108.4,"t":"哦，是一個。"},{"s":2108.4,"e":2111.5,"t":"買點，哦，是一個買點。"},{"s":2111.5,"e":2112.5,"t":"如果你為。"},{"s":2112.5,"e":2119.09,"t":"沒辦法看盤的話，哦，那你就把這個上軌哈去乘以零點九九，哈，它可能就會是一個比較安全的。"},{"s":2119.09,"e":2123.85,"t":"一個位置，好，股價還有機會可以到這個位置，瞭解我意思嗎？哦。"},{"s":2123.85,"e":2124.85,"t":"這個。"},{"s":2124.85,"e":2132.02,"t":"這個算是比較一個進階的一個，呃，的操作方式啊，就是你非常相信這個，這個。"},{"s":2132.02,"e":2137.54,"t":"它會打到上軌，而且不會往上噴，那你就可以看一下，哎，因為每次每天開盤。"},{"s":2137.54,"e":2138.54,"t":"他都會上。"},{"s":2138.54,"e":2147.59,"t":"尾的位價格就會出來了，呃，這個這個部分可能，呃，你要去問一下你的營業員，瞭解一下，或者是等我們在那個。"},{"s":2147.59,"e":2153.5,"t":"課後的，呃，輔導的群組裡面的時候，我們可以針對這個部分做詳解。"},{"s":2153.5,"e":2159.48,"t":"你要就意思嘛？哈，開盤的時候你會得到一個上軌的價格，好，開盤價出來的時候，你就有上軌的價格。"},{"s":2159.48,"e":2160.48,"t":"好，上軌。"},{"s":2160.48,"e":2161.57,"t":"的價格去乘以。"},{"s":2161.57,"e":2171.52,"t":"零點九九，哎，它有可能就是今天如果下殺的時候，哦，它可能會碰到的位置。好，如果它前面都符合的話，它在這個地方可以得到一個支撐。"},{"s":2171.52,"e":2177.5,"t":"好，這詳細的話，我們可以再實測看看。再來下一個。"},{"s":2177.5,"e":2185.54,"t":"收盤價實體綠K好，跌到上軌之內的時候做賣出。"},{"s":2185.54,"e":2186.54,"t":"嗯。"},{"s":2186.54,"e":2188.09,"t":"這樣。"},{"s":2188.09,"e":2194.09,"t":"原本都在股價都在上軌之上，對不對？但是它哪一天，它的它收盤價在上軌？"},{"s":2194.09,"e":2203.59,"t":"上軌的下面的時候，好，那就是一個模擬出場的位置了，就是這筆交易模模擬交易的出場的位置，瞭解意思嗎？"},{"s":2203.59,"e":2211.85,"t":"好，股價齊漲或齊跌的特色啊，就是布林通道會從窄的時候變長，變成是喇叭的形狀。"},{"s":2211.85,"e":2219.35,"t":"OK，好，那我們這個廢話不多說啊，我們直接帶案例，你絕對就可以瞭解。"},{"s":2219.35,"e":2227.59,"t":"好，再來六六七二騰輝電子，在五月二十八號的時候，我們在這個地方有發現到，它已經怎麼樣？"},{"s":2227.59,"e":2235.85,"t":"帶量的突出了上軌，好，帶量的突出了上軌，對不對？"},{"s":2235.85,"e":2236.85,"t":"這個位置。"},{"s":2236.85,"e":2240.09,"t":"好，再讓圖上軌這種哈。"},{"s":2240.09,"e":2247.85,"t":"前面他已經還沒有沒有做壓縮的，但是他這個圖確認圖出去，為什麼嘞？因為，它有帶量。"},{"s":2247.85,"e":2252.84,"t":"有帶量，瞭解意思嗎？哦，所以我們可以在這天的尾盤。"},{"s":2252.84,"e":2261.51,"t":"進行切入啊，模擬切入啊，下一個就是變成來看一下哦，這邊。"},{"s":2261.51,"e":2264.24,"t":"看一下這邊。"},{"s":2264.24,"e":2272.03,"t":"隔一天，你可以去算一下哈，隔一天上軌的價格去乘以零點九九，或者是上軌的價格和它的低點。"},{"s":2272.03,"e":2280.24,"t":"這一根的低點，哦，六月一號這個附近，好，是不是差不多吻合的？好，為什麼會有這個現象嘞？"},{"s":2280.24,"e":2289.5,"t":"非常的簡單，因為它的前一天是出量的，站上上軌，收盤價在上軌之上。"},{"s":2289.5,"e":2293.74,"t":"後續，它的上軌就會具備。"},{"s":2293.74,"e":2301.24,"t":"支撐多方的支撐買盤，瞭解我意思嗎？就是這樣看，它吐出去上軌，它必須要。"},{"s":2301.24,"e":2306.91,"t":"出量哦，哦，這樣子它的那個支撐才有有出來，瞭解我意思嗎？"},{"s":2306.91,"e":2315.07,"t":"OK，一路這樣走走走走走走走到這個地方，好，離開了上軌，收盤價離開上軌。"},{"s":2315.07,"e":2323.18,"t":"短線陷入可能陷入三到五天的整理，哎，我們短線漲幅這也夠了，從一百到一百三，一百到一百三，只有。"},{"s":2323.18,"e":2325.74,"t":"兩誒，兩週。"},{"s":2325.74,"e":2331.24,"t":"好，大概八個交易日左右，一二三四五六七八，對，八天。"},{"s":2331.24,"e":2339.18,"t":"好，你八天就從一百到一百三了，好，就賺這中間三十塊，好，三十塊也很夠用了，也很夠用了，好。"},{"s":2339.18,"e":2341.74,"t":"很有效率了，應該說非常有效率了。"},{"s":2341.74,"e":2349.24,"t":"好，再來下一個。好，金豪科，金豪科，來，在這一天。"},{"s":2349.24,"e":2355.15,"t":"二月二零二一年的二月十七號，你在這邊可以發現金豪哥。"},{"s":2355.15,"e":2363.18,"t":"好，那你不你因為你是盤後發現嘛，對不對？我們是盤後發現，一定是隔天才能把它拿出來做觀察。"},{"s":2363.18,"e":2371.18,"t":"對不對哦？所以隔天的時候，發現一件事情，它帶量的怎麼樣？一樣跟剛剛的形態。"},{"s":2371.18,"e":2372.18,"t":"一模一樣。"},{"s":2372.18,"e":2379.18,"t":"對不對？出量站上了上軌，出量站上了上軌，你可以在這一天的什麼？"},{"s":2379.18,"e":2387.24,"t":"尾盤就進行切入，你可以在今天的尾盤就進行切入，對吧？好，所以我這邊教學就是，我們第一步。"},{"s":2387.24,"e":2388.24,"t":"嗯。"},{"s":2388.24,"e":2394.5,"t":"好，先用頭性，先用頭性來去做選擇。"},{"s":2394.5,"e":2401.48,"t":"好，篩選完之後，你放到你你覺得，哎，他明天有機會的標的裡面之後。"},{"s":2401.48,"e":2405.24,"t":"到他自選，哦，你到自選裡面，哎，尾盤的時候。"},{"s":2405.24,"e":2411.74,"t":"來確認一下，他是不是有符合我們所教的目前這幾個、這三個的一個情況。"},{"s":2411.74,"e":2417.5,"t":"瞭解意思嗎？好，這都非常的有機會。好，好，在這邊。"},{"s":2417.5,"e":2421,"t":"好，直接往上拉哦，七十到九十。"},{"s":2421,"e":2429.05,"t":"好，這邊是那個離開了上軌K棒的離開了上軌，短線可能陷入兩到三天的整理，那我們就可以先離場，後面的。"},{"s":2429.05,"e":2437.5,"t":"找進場點，對不對？哦，這樣就是一個很完整的一個呃短短線的交易，就這麼簡單。"},{"s":2437.5,"e":2445.5,"t":"好，一二三四五六七七天，哦，七天從七十到九十，七天從七十到九十。"},{"s":2445.5,"e":2451.18,"t":"OK，好，上軌都去支撐了，有沒有看到？"},{"s":2451.18,"e":2452.18,"t":"是。"},{"s":2452.18,"e":2461.74,"t":"上軌都有支撐，每天達到上軌都有支撐。OK，好，重點在於說它一開始已經有帶量的站上上軌了。"},{"s":2461.74,"e":2463.14,"t":"所以，他才會有這個。"},{"s":2463.14,"e":2473.09,"t":"特性，懂嗎？這是雙呃布林是一個雙面刃，布林是一個雙面刃。好，你要麼一定要跳出去。"},{"s":2473.09,"e":2474.09,"t":"嗯。"},{"s":2474.09,"e":2483.74,"t":"股價一定要跳出去，哦，不然如果你在裡面的話，在上軌之內的話，就會被股價往下打，就會被上軌往下打。"},{"s":2483.74,"e":2485.74,"t":"這是上通道。"},{"s":2485.74,"e":2493.51,"t":"你要麼就一定要跳出去，好，不然你就回到下面去。為什麼？因為只要股價在下。"},{"s":2493.51,"e":2501.5,"t":"上軌之下的話，股價哦，股價在上軌之下的話，哎，這邊注意看。"},{"s":2501.5,"e":2507.18,"t":"有沒有股價在上軌之下的時候，就很容易形成什麼？"},{"s":2507.18,"e":2508.18,"t":"麥芽。"},{"s":2508.18,"e":2517.5,"t":"這是一個雙面刃，懂嗎？所以我希望他趕快跳出去，趕快的跳出去，就可以變成另外一種格局。"},{"s":2517.5,"e":2523.15,"t":"另外一種就是他轉型了，他突然轉型了，瞭解我意思嗎？他轉型了。"},{"s":2523.15,"e":2530.92,"t":"好，下一個，好，一樣，完全一模一樣的情況，對不對？好，華訊在這一天一樣。"},{"s":2530.92,"e":2534.49,"t":"好，盤後的時候看到它了。好，看到它了。"},{"s":2534.49,"e":2535.49,"t":"帶量的。"},{"s":2535.49,"e":2543.16,"t":"站上了上軌，好，隔天我們注意它，好，隔天我們注意它，對不對？帶上這行，我們隔天注意它。"},{"s":2543.16,"e":2545.89,"t":"因為我們這是盤後嘛，好。"},{"s":2545.89,"e":2549.39,"t":"哎，好，隔天怎麼樣？"},{"s":2549.39,"e":2556.89,"t":"初量的站上了上軌，初量的站上了上軌。"},{"s":2556.89,"e":2560.28,"t":"這邊。"},{"s":2560.28,"e":2562.89,"t":"出量站上上軌了。"},{"s":2562.89,"e":2571.15,"t":"好，我們前前幾天看到了。好，其實我們在更早的時候就有發現到它。"},{"s":2571.15,"e":2580.83,"t":"好，更早的時候就發現到它，對不對？"},{"s":2580.83,"e":2581.83,"t":"嗯。"},{"s":2581.83,"e":2591.15,"t":"哦，這邊這邊哦，然後我記得我是寫在，呃，十二月二十七附近。"},{"s":2591.15,"e":2596.89,"t":"好，我們看一下。好，這邊哦，沒錯哈，同學們們看到。"},{"s":2596.89,"e":2603.15,"t":"好，六二三七哦，華訊哦，華訊，在這個位置，哎，我發現到它。"},{"s":2603.15,"e":2604.15,"t":"有籌碼的。"},{"s":2604.15,"e":2610.89,"t":"的一個情況，哦，有籌碼的情況，但是我們這個看到的是一個主力的情況，哦，主力的情況。"},{"s":2610.89,"e":2615.39,"t":"哎，後續有開始留意到，他投信。"},{"s":2615.39,"e":2623.39,"t":"有加入進來，好，那我們就有籌碼的一個啊，籌碼的一個追蹤，哦，籌碼的一個追蹤，十二月二十七號。"},{"s":2623.39,"e":2631.39,"t":"十月二十七號，好，這是上一次，呃，去年這一段做的還不錯的，哦，做的還不錯的，好，到現在。"},{"s":2631.39,"e":2636.83,"t":"到目前為止，他都還沒有走完哦。當時有做一個影音的。"},{"s":2636.83,"e":2637.83,"t":"介紹。"},{"s":2637.83,"e":2646.75,"t":"哦，選股邏輯又做一個影音的介紹，啊，又講到我們如何利用上軌，還有頭性，啊，因為我們一開始是用這個主力券商。"},{"s":2646.75,"e":2650.74,"t":"去發現到他，哎，後面開始投信加入進來了。"},{"s":2650.74,"e":2652.13,"t":"啊，我們就做一個。"},{"s":2652.13,"e":2660.83,"t":"完整的一個"}]